log_dynamo/__init__.py
log_dynamo/access.py
log_dynamo/level.py
log_dynamo/record.py
log_dynamo/utils.py
log_dynamo-0.1.5.dist-info/WHEEL
log_dynamo-0.1.5.dist-info/METADATA
log_dynamo-0.1.5.dist-info/RECORD
