Metadata-Version: 2.3
Name: log-dynamo
Version: 0.1.5
Summary: Log by DynamoDB
Requires-Dist: boto3
Requires-Python: >=3.10
